manage_switches/All.py
manage_switches/DoConcurrent.py
manage_switches/DocFunctions.py
manage_switches/NetworkFunctions.py
manage_switches/SwitchFunctions.py
manage_switches/__init__.py
net_switch_tools-0.0.3.dist-info/LICENSE
net_switch_tools-0.0.3.dist-info/METADATA
net_switch_tools-0.0.3.dist-info/WHEEL
net_switch_tools-0.0.3.dist-info/top_level.txt
net_switch_tools-0.0.3.dist-info/RECORD
