Metadata-Version: 2.1
Name: net-switch-tools
Version: 0.0.3
Summary: A package for managing network switches
Home-page: https://github.com/greenfructose/net-switch-tools
Author: Justin Turney
Author-email: info@justinturney.com
License: UNKNOWN
Project-URL: Bug Tracker, https://github.com/greenfructose/net-switch-tools/issues
Platform: UNKNOWN
Classifier: Programming Language :: Python :: 3
Classifier: License :: OSI Approved :: MIT License
Classifier: Operating System :: OS Independent
Requires-Python: >=3.6
License-File: LICENSE
